[{"id": 1368050, "name": "Candi", "position": "Left-Back", "dateOfBirth": "", "nationality": ["Spain"], "leagues": {"La Liga": {"apps": 0, "debut": ""}}}, {"id": 1368085, "name": "Jock Watson", "position": "", "dateOfBirth": "28.11.1883", "nationality": ["Scotland"], "clubs": {"Newcastle United": {"apps": 3, "goals": 0, "assists": 0, "ownGoals": 0, "yellowCards": 0, "secondYellows": 0, "redCards": 0, "subOn": 0, "subOff": 0, "minutes": 270}}}, {"id": 1368089, "name": "Pere Pla", "position": "Defender", "dateOfBirth": "", "nationality": ["Spain"], "leagues": {"La Liga": {"debutClub": "Granada CF", "debutAgainst": "Real Sociedad", "debutDate": "12.09.1971", "debutResult": "3:1", "debutOutcome": "loss", "ageAtDebut": "20 years 02 months 18 days", "apps": 10, "debut": "12/09/1971"}}}, {"id": 1368106, "name": "Harry Stenhouse", "position": "", "dateOfBirth": "01.01.1882", "nationality": ["England"], "clubs": {"Newcastle United": {"apps": 6, "goals": 0, "assists": 0, "ownGoals": 0, "yellowCards": 0, "secondYellows": 0, "redCards": 0, "subOn": 0, "subOff": 0, "minutes": 540}}}, {"id": 1368116, "name": "Max Kerkvliet", "position": "Goalkeeper", "dateOfBirth": "", "nationality": ["United States"], "leagues": {"MLS": {"apps": 0, "debut": ""}}}, {"id": 1368161, "name": "José Fernández", "position": "Goalkeeper", "dateOfBirth": "", "nationality": ["Spain"], "leagues": {"La Liga": {"debutClub": "Elche CF", "debutAgainst": "Cádiz CF", "debutDate": "07.05.1978", "debutResult": "0:0", "debutOutcome": "draw", "ageAtDebut": "22 years 11 months 18 days", "apps": 1, "debut": "07/05/1978"}}}, {"id": 1368162, "name": "Bartolomé Bennásar", "position": "Goalkeeper", "dateOfBirth": "", "nationality": ["Spain"], "leagues": {"La Liga": {"debutClub": "Club Real Murcia", "debutAgainst": "Sporting Gijón", "debutDate": "16.11.1980", "debutResult": "2:0", "debutOutcome": "loss", "ageAtDebut": "24 years 07 months 11 days", "apps": 1, "debut": "16/11/1980"}}}, {"id": 1368163, "name": "Savino", "position": "Forward", "dateOfBirth": "", "nationality": ["Spain"], "leagues": {"La Liga": {"debutClub": "Hércules CF", "debutAgainst": "Elche CF", "debutDate": "09.09.1984", "debutResult": "1:0", "debutOutcome": "win", "ageAtDebut": "17 years 04 months 29 days", "apps": 1, "debut": "09/09/1984"}}}, {"id": 1368164, "name": "Francisco José Esteve", "position": "Forward", "dateOfBirth": "", "nationality": ["Spain"], "leagues": {"La Liga": {"debutClub": "Hércules CF", "debutAgainst": "Elche CF", "debutDate": "09.09.1984", "debutResult": "1:0", "debutOutcome": "win", "ageAtDebut": "17 years 11 months 26 days", "apps": 1, "debut": "09/09/1984"}}}, {"id": 1368165, "name": "N. N. Romero", "position": "Forward", "dateOfBirth": "", "nationality": ["Spain"], "leagues": {"La Liga": {"debutClub": "Elche CF", "debutAgainst": "Hércules CF", "debutDate": "09.09.1984", "debutResult": "1:0", "debutOutcome": "loss", "ageAtDebut": "-", "apps": 1, "debut": "09/09/1984"}}}, {"id": 1368166, "name": "N. N. Cota", "position": "Forward", "dateOfBirth": "", "nationality": ["Spain"], "leagues": {"La Liga": {"debutClub": "Elche CF", "debutAgainst": "Hércules CF", "debutDate": "09.09.1984", "debutResult": "1:0", "debutOutcome": "loss", "ageAtDebut": "-", "apps": 1, "debut": "09/09/1984"}}}, {"id": 1368167, "name": "Antonio", "position": "Midfielder", "dateOfBirth": "", "nationality": ["Spain"], "leagues": {"La Liga": {"debutClub": "Elche CF", "debutAgainst": "Hércules CF", "debutDate": "09.09.1984", "debutResult": "1:0", "debutOutcome": "loss", "ageAtDebut": "19 years 07 months 24 days", "apps": 1, "debut": "09/09/1984"}}}, {"id": 1368168, "name": "N. N. Alberola", "position": "Forward", "dateOfBirth": "", "nationality": ["Spain"], "leagues": {"La Liga": {"debutClub": "Elche CF", "debutAgainst": "Hércules CF", "debutDate": "09.09.1984", "debutResult": "1:0", "debutOutcome": "loss", "ageAtDebut": "-", "apps": 1, "debut": "09/09/1984"}}}, {"id": 1368170, "name": "José Carlos Carrasco", "position": "Goalkeeper", "dateOfBirth": "", "nationality": ["Spain"], "leagues": {"La Liga": {"debutClub": "Real Murcia CF", "debutAgainst": "Real Betis Balompié", "debutDate": "09.09.1984", "debutResult": "0:1", "debutOutcome": "loss", "ageAtDebut": "23 years 00 days", "apps": 1, "debut": "09/09/1984"}}}, {"id": 1368171, "name": "Villayón", "position": "Defender", "dateOfBirth": "", "nationality": ["Spain"], "leagues": {"La Liga": {"debutClub": "Real Murcia CF", "debutAgainst": "Real Betis Balompié", "debutDate": "09.09.1984", "debutResult": "0:1", "debutOutcome": "loss", "ageAtDebut": "19 years 12 days", "apps": 1, "debut": "09/09/1984"}}}, {"id": 1368172, "name": "Francis", "position": "Defender", "dateOfBirth": "", "nationality": ["Spain"], "leagues": {"La Liga": {"debutClub": "Real Murcia CF", "debutAgainst": "Real Betis Balompié", "debutDate": "09.09.1984", "debutResult": "0:1", "debutOutcome": "loss", "ageAtDebut": "22 years 02 months 26 days", "apps": 1, "debut": "09/09/1984"}}}, {"id": 1368173, "name": "N. N. Galván", "position": "Midfielder", "dateOfBirth": "", "nationality": ["Spain"], "leagues": {"La Liga": {"debutClub": "Real Murcia CF", "debutAgainst": "Real Betis Balompié", "debutDate": "09.09.1984", "debutResult": "0:1", "debutOutcome": "loss", "ageAtDebut": "-", "apps": 1, "debut": "09/09/1984"}}}, {"id": 1368174, "name": "Tomás", "position": "Forward", "dateOfBirth": "", "nationality": ["Spain"], "leagues": {"La Liga": {"debutClub": "Real Murcia CF", "debutAgainst": "Real Betis Balompié", "debutDate": "09.09.1984", "debutResult": "0:1", "debutOutcome": "loss", "ageAtDebut": "23 years 11 months 02 days", "apps": 1, "debut": "09/09/1984"}}}, {"id": 1368175, "name": "José Juan Manzanares", "position": "Midfielder", "dateOfBirth": "", "nationality": ["Spain"], "leagues": {"La Liga": {"debutClub": "Real Murcia CF", "debutAgainst": "Real Betis Balompié", "debutDate": "09.09.1984", "debutResult": "0:1", "debutOutcome": "loss", "ageAtDebut": "18 years 06 months 24 days", "apps": 1, "debut": "09/09/1984"}}}, {"id": 1368176, "name": "Francisco Nicolás", "position": "Midfielder", "dateOfBirth": "", "nationality": ["Spain"], "leagues": {"La Liga": {"debutClub": "Real Murcia CF", "debutAgainst": "Real Betis Balompié", "debutDate": "09.09.1984", "debutResult": "0:1", "debutOutcome": "loss", "ageAtDebut": "22 years 04 days", "apps": 1, "debut": "09/09/1984"}}}, {"id": 1368177, "name": "Francisco Marín", "position": "Defender", "dateOfBirth": "02.02.1964", "nationality": ["Spain"], "clubs": {"Real Betis": {"apps": 1, "goals": 0, "assists": 0, "ownGoals": 0, "yellowCards": 0, "secondYellows": 0, "redCards": 0, "subOn": 0, "subOff": 0, "minutes": 90}}, "leagues": {"La Liga": {"debutClub": "Real Betis Balompié", "debutAgainst": "Real Murcia CF", "debutDate": "09.09.1984", "debutResult": "0:1", "debutOutcome": "win", "ageAtDebut": "20 years 07 months 07 days", "apps": 1, "debut": "09/09/1984"}}}, {"id": 1368178, "name": "Ríscar", "position": "Defender", "dateOfBirth": "20.05.1962", "nationality": ["Spain"], "clubs": {"Real Betis": {"apps": 1, "goals": 0, "assists": 0, "ownGoals": 0, "yellowCards": 0, "secondYellows": 0, "redCards": 0, "subOn": 0, "subOff": 0, "minutes": 90}}, "leagues": {"La Liga": {"debutClub": "Real Betis Balompié", "debutAgainst": "Real Murcia CF", "debutDate": "09.09.1984", "debutResult": "0:1", "debutOutcome": "win", "ageAtDebut": "22 years 03 months 20 days", "apps": 1, "debut": "09/09/1984"}}}, {"id": 1368194, "name": "Miguel Ángel", "position": "Forward", "dateOfBirth": "", "nationality": ["Spain"], "leagues": {"La Liga": {"debutClub": "Real Murcia CF", "debutAgainst": "Athletic Bilbao", "debutDate": "04.10.1987", "debutResult": "2:3", "debutOutcome": "loss", "ageAtDebut": "20 years 03 months 08 days", "apps": 1, "debut": "04/10/1987"}}}, {"id": 1368230, "name": "José Luis Zunino", "position": "Defender", "dateOfBirth": "", "nationality": ["Spain"], "leagues": {"La Liga": {"debutClub": "Granada CF", "debutAgainst": "Real Zaragoza", "debutDate": "02.09.1972", "debutResult": "0:0", "debutOutcome": "draw", "ageAtDebut": "24 years 04 months 02 days", "apps": 1, "debut": "02/09/1972"}}}, {"id": 1368234, "name": "José Ramón Moncaleán", "position": "Goalkeeper", "dateOfBirth": "", "nationality": ["Spain"], "leagues": {"La Liga": {"apps": 0, "debut": ""}}}, {"id": 1368239, "name": "José Antonio González", "position": "Defender", "dateOfBirth": "", "nationality": ["Spain"], "leagues": {"La Liga": {"debutClub": "Celta de Vigo", "debutAgainst": "CE Sabadell FC", "debutDate": "21.09.1969", "debutResult": "1:1", "debutOutcome": "draw", "ageAtDebut": "26 years 02 months 08 days", "apps": 2, "debut": "21/09/1969"}}}, {"id": 1368243, "name": "Pedro María Aramburuzabala", "position": "Defender", "dateOfBirth": "", "nationality": ["Spain"], "leagues": {"La Liga": {"debutClub": "Burgos CF", "debutAgainst": "Málaga CF", "debutDate": "26.09.1971", "debutResult": "4:1", "debutOutcome": "loss", "ageAtDebut": "26 years 04 months 13 days", "apps": 2, "debut": "26/09/1971"}}}, {"id": 1368244, "name": "Antonio Manuel Yáñez", "position": "Defender", "dateOfBirth": "", "nationality": ["Spain"], "leagues": {"La Liga": {"debutClub": "Celta de Vigo", "debutAgainst": "Real Sociedad", "debutDate": "17.09.1972", "debutResult": "0:1", "debutOutcome": "loss", "ageAtDebut": "24 years 04 months 08 days", "apps": 3, "debut": "17/09/1972"}}}, {"id": 1368245, "name": "Waldo Otero", "position": "Forward", "dateOfBirth": "", "nationality": ["Spain"], "leagues": {"La Liga": {"debutClub": "Celta de Vigo", "debutAgainst": "Real Sociedad", "debutDate": "17.09.1972", "debutResult": "0:1", "debutOutcome": "loss", "ageAtDebut": "21 years 07 months 17 days", "apps": 2, "debut": "17/09/1972"}}}, {"id": 1368246, "name": "Tucho", "position": "Midfielder", "dateOfBirth": "", "nationality": ["Spain"], "leagues": {"La Liga": {"apps": 0, "debut": ""}}}, {"id": 1368250, "name": "Fermín Miñán", "position": "Goalkeeper", "dateOfBirth": "", "nationality": ["Spain"], "leagues": {"La Liga": {"apps": 0, "debut": ""}}}, {"id": 1368254, "name": "Fernández Flórez", "position": "Defender", "dateOfBirth": "02.03.1948", "nationality": ["Spain"], "clubs": {"Real Betis": {"apps": 4, "goals": 0, "assists": 0, "ownGoals": 0, "yellowCards": 1, "secondYellows": 0, "redCards": 0, "subOn": 1, "subOff": 1, "minutes": 281}}, "leagues": {"La Liga": {"debutClub": "Real Betis Balompié", "debutAgainst": "Granada CF", "debutDate": "01.10.1972", "debutResult": "0:0", "debutOutcome": "draw", "ageAtDebut": "24 years 06 months 29 days", "apps": 4, "debut": "01/10/1972"}}}, {"id": 1368263, "name": "Salvador Bustamante", "position": "Midfielder", "dateOfBirth": "", "nationality": ["Spain"], "leagues": {"La Liga": {"apps": 0, "debut": ""}}}, {"id": 1368297, "name": "Albert Tuyp", "position": "Midfielder", "dateOfBirth": "", "nationality": ["Netherlands"], "leagues": {"Eredivisie": {"debutClub": "RKSV Volendam", "debutAgainst": "FC Volendam", "debutDate": "16.06.1963", "debutResult": "1:2", "debutOutcome": "loss", "ageAtDebut": "19 years 01 month 27 days", "apps": 11, "debut": "16/06/1963"}}}, {"id": 1368311, "name": "Ramón Canedo", "position": "Goalkeeper", "dateOfBirth": "", "nationality": ["Spain"], "leagues": {"La Liga": {"apps": 0, "debut": ""}}}, {"id": 1368312, "name": "Japo", "position": "Forward", "dateOfBirth": "", "nationality": ["Spain"], "leagues": {"La Liga": {"debutClub": "Real Oviedo CF", "debutAgainst": "Real Oviedo", "debutDate": "19.11.1972", "debutResult": "1:2", "debutOutcome": "loss", "ageAtDebut": "25 years 04 months 21 days", "apps": 2, "debut": "19/11/1972"}}}, {"id": 1368396, "name": "Rodolfo Rivero", "position": "Forward", "dateOfBirth": "", "nationality": ["Spain"], "leagues": {"La Liga": {"debutClub": "RCD Español", "debutAgainst": "RCD Espanyol Barcelona", "debutDate": "07.01.1973", "debutResult": "1:0", "debutOutcome": "win", "ageAtDebut": "23 years 07 months 26 days", "apps": 2, "debut": "07/01/1973"}}}, {"id": 1368402, "name": "Jan Karhof", "position": "Right Midfield", "dateOfBirth": "", "nationality": ["Netherlands"], "leagues": {"Eredivisie": {"debutClub": "USV Elinkwijk", "debutAgainst": "SC Telstar", "debutDate": "06.03.1966", "debutResult": "3:1", "debutOutcome": "loss", "ageAtDebut": "26 years 04 months 21 days", "apps": 2, "debut": "06/03/1966"}}}, {"id": 1368403, "name": "N. N. Westers", "position": "Midfielder", "dateOfBirth": "", "nationality": ["Netherlands"], "leagues": {"Eredivisie": {"debutClub": "DOS BV Utrecht", "debutAgainst": "Sparta Rotterdam", "debutDate": "26.12.1965", "debutResult": "3:1", "debutOutcome": "loss", "ageAtDebut": "-", "apps": 1, "debut": "26/12/1965"}}}, {"id": 1368409, "name": "Rinus Hondelink", "position": "Defender", "dateOfBirth": "", "nationality": ["Netherlands"], "leagues": {"Eredivisie": {"debutClub": "Go Ahead", "debutAgainst": "Go Ahead Eagles", "debutDate": "25.08.1963", "debutResult": "1:3", "debutOutcome": "loss", "ageAtDebut": "24 years 03 months 22 days", "apps": 32, "debut": "25/08/1963"}}}, {"id": 1368433, "name": "Santiago Chicharro", "position": "Goalkeeper", "dateOfBirth": "15.05.1948", "nationality": ["Spain"], "clubs": {"Real Betis": {"apps": 3, "goals": 0, "assists": 0, "ownGoals": 0, "yellowCards": 0, "secondYellows": 0, "redCards": 0, "subOn": 1, "subOff": 1, "minutes": 181}}, "leagues": {"La Liga": {"debutClub": "Real Betis Balompié", "debutAgainst": "Real Zaragoza", "debutDate": "04.03.1973", "debutResult": "3:2", "debutOutcome": "loss", "ageAtDebut": "24 years 09 months 17 days", "apps": 3, "debut": "04/03/1973"}}}, {"id": 1368453, "name": "Jo Vrösch", "position": "Midfielder", "dateOfBirth": "", "nationality": ["Netherlands"], "leagues": {"Eredivisie": {"debutClub": "MVV Maastricht", "debutAgainst": "Heracles Almelo", "debutDate": "23.08.1964", "debutResult": "3:2", "debutOutcome": "loss", "ageAtDebut": "20 years 10 months 19 days", "apps": 20, "debut": "23/08/1964"}}}, {"id": 1368455, "name": "Pierre Roukens", "position": "Right-Back", "dateOfBirth": "", "nationality": ["Netherlands"], "leagues": {"Eredivisie": {"debutClub": "MVV Maastricht", "debutAgainst": "PSV Eindhoven", "debutDate": "27.09.1964", "debutResult": "0:3", "debutOutcome": "loss", "ageAtDebut": "23 years 04 months 09 days", "apps": 38, "debut": "27/09/1964"}}}, {"id": 1368457, "name": "Willy Smeets", "position": "Left Winger", "dateOfBirth": "", "nationality": ["Netherlands"], "leagues": {"Eredivisie": {"debutClub": "MVV Maastricht", "debutAgainst": "FC Groningen", "debutDate": "20.09.1964", "debutResult": "5:2", "debutOutcome": "loss", "ageAtDebut": "18 years 11 months 29 days", "apps": 3, "debut": "20/09/1964"}}}, {"id": 1368484, "name": "Wilson", "position": "Forward", "dateOfBirth": "", "nationality": ["Brazil"], "leagues": {"Eredivisie": {"debutClub": "SC Telstar", "debutAgainst": "Twente Enschede FC", "debutDate": "06.02.1966", "debutResult": "1:0", "debutOutcome": "win", "ageAtDebut": "23 years 04 days", "apps": 1, "debut": "06/02/1966"}}}, {"id": 1368508, "name": "Herman Tijssen", "position": "Defender", "dateOfBirth": "", "nationality": ["Netherlands"], "leagues": {"Eredivisie": {"debutClub": "Willem II", "debutAgainst": "Willem II Tilburg", "debutDate": "10.10.1965", "debutResult": "4:0", "debutOutcome": "win", "ageAtDebut": "23 years 03 months 21 days", "apps": 4, "debut": "10/10/1965"}}}, {"id": 1368613, "name": "Juárez", "position": "Defender", "dateOfBirth": "", "nationality": ["Spain"], "leagues": {"La Liga": {"debutClub": "Córdoba CF", "debutAgainst": "Deportivo de La Coruña", "debutDate": "05.09.1971", "debutResult": "3:2", "debutOutcome": "loss", "ageAtDebut": "20 years 06 months 22 days", "apps": 1, "debut": "05/09/1971"}}}, {"id": 1368624, "name": "Rene Letterboom", "position": "Forward", "dateOfBirth": "", "nationality": ["Netherlands"], "leagues": {"Eredivisie": {"apps": 0, "debut": ""}}}, {"id": 1368625, "name": "Cornelius Johnson", "position": "Defender", "dateOfBirth": "", "nationality": ["Netherlands"], "leagues": {"Eredivisie": {"debutClub": "BVV", "debutAgainst": "FC Den Bosch", "debutDate": "25.08.1957", "debutResult": "2:2", "debutOutcome": "draw", "ageAtDebut": "25 years 29 days", "apps": 25, "debut": "25/08/1957"}}}, {"id": 1368630, "name": "Piet Koekebakker", "position": "Centre-Forward", "dateOfBirth": "", "nationality": ["Netherlands"], "leagues": {"Eredivisie": {"debutClub": "SV Blauw-Wit", "debutAgainst": "VVV-Venlo", "debutDate": "25.08.1957", "debutResult": "2:0", "debutOutcome": "loss", "ageAtDebut": "33 years 04 months 22 days", "apps": 32, "debut": "25/08/1957"}}}, {"id": 1368633, "name": "Joop Bommels", "position": "Forward", "dateOfBirth": "", "nationality": ["Netherlands"], "leagues": {"Eredivisie": {"debutClub": "SV Blauw-Wit", "debutAgainst": "ASV Blauw-Wit", "debutDate": "01.09.1957", "debutResult": "1:2", "debutOutcome": "loss", "ageAtDebut": "21 years 05 months 26 days", "apps": 4, "debut": "01/09/1957"}}}, {"id": 1368637, "name": "Karel Diehl", "position": "Forward", "dateOfBirth": "", "nationality": ["Netherlands"], "leagues": {"Eredivisie": {"debutClub": "SV Blauw-Wit", "debutAgainst": "Feyenoord Rotterdam", "debutDate": "08.09.1957", "debutResult": "3:1", "debutOutcome": "loss", "ageAtDebut": "21 years 09 months 20 days", "apps": 12, "debut": "08/09/1957"}}}, {"id": 1368642, "name": "Dor Loormans", "position": "Forward", "dateOfBirth": "", "nationality": ["Netherlands"], "leagues": {"Eredivisie": {"debutClub": "MVV Maastricht", "debutAgainst": "USV Elinkwijk", "debutDate": "01.09.1957", "debutResult": "6:2", "debutOutcome": "win", "ageAtDebut": "19 years 10 months 17 days", "apps": 1, "debut": "01/09/1957"}}}, {"id": 1368643, "name": "Freddy Mees", "position": "Midfielder", "dateOfBirth": "", "nationality": ["Netherlands"], "leagues": {"Eredivisie": {"debutClub": "USV Elinkwijk", "debutAgainst": "MVV Maastricht", "debutDate": "01.09.1957", "debutResult": "6:2", "debutOutcome": "loss", "ageAtDebut": "26 years 03 months 17 days", "apps": 31, "debut": "01/09/1957"}}}, {"id": 1368644, "name": "Jos Berkelmans", "position": "Forward", "dateOfBirth": "", "nationality": ["Netherlands"], "leagues": {"Eredivisie": {"debutClub": "BVV", "debutAgainst": "FC Den Bosch", "debutDate": "08.09.1957", "debutResult": "2:2", "debutOutcome": "draw", "ageAtDebut": "21 years 05 months 00 days", "apps": 27, "debut": "08/09/1957"}}}, {"id": 1368657, "name": "Aad van der Zant", "position": "Forward", "dateOfBirth": "", "nationality": ["Netherlands"], "leagues": {"Eredivisie": {"debutClub": "SV Blauw-Wit", "debutAgainst": "ASV Blauw-Wit", "debutDate": "15.09.1957", "debutResult": "3:3", "debutOutcome": "draw", "ageAtDebut": "27 years 05 months 07 days", "apps": 19, "debut": "15/09/1957"}}}, {"id": 1368669, "name": "Carmelo", "position": "Goalkeeper", "dateOfBirth": "18.11.1946", "nationality": ["Spain"], "clubs": {"Sevilla FC": {"apps": 3, "goals": 0, "assists": 0, "ownGoals": 0, "yellowCards": 1, "secondYellows": 0, "redCards": 0, "subOn": 1, "subOff": 0, "minutes": 237}}, "leagues": {"La Liga": {"debutClub": "Sevilla FC", "debutAgainst": "Real Sociedad", "debutDate": "26.09.1971", "debutResult": "1:1", "debutOutcome": "draw", "ageAtDebut": "24 years 10 months 08 days", "apps": 3, "debut": "26/09/1971"}}}, {"id": 1368710, "name": "Daniel Haanskorf", "position": "Forward", "dateOfBirth": "", "nationality": ["Netherlands"], "leagues": {"Eredivisie": {"debutClub": "NAC", "debutAgainst": "Sparta Rotterdam", "debutDate": "29.09.1957", "debutResult": "0:1", "debutOutcome": "win", "ageAtDebut": "19 years 00 days", "apps": 3, "debut": "29/09/1957"}}}, {"id": 1368711, "name": "Peter Eysens", "position": "Midfielder", "dateOfBirth": "", "nationality": ["Netherlands"], "leagues": {"Eredivisie": {"debutClub": "MVV Maastricht", "debutAgainst": "BVC Amsterdam (- 1958)", "debutDate": "06.10.1957", "debutResult": "3:2", "debutOutcome": "loss", "ageAtDebut": "-", "apps": 1, "debut": "06/10/1957"}}}, {"id": 1368714, "name": "Henk Staps", "position": "Forward", "dateOfBirth": "", "nationality": ["Netherlands"], "leagues": {"Eredivisie": {"debutClub": "NOAD Tilburg", "debutAgainst": "NAC Breda", "debutDate": "08.12.1957", "debutResult": "4:0", "debutOutcome": "loss", "ageAtDebut": "21 years 02 months 16 days", "apps": 7, "debut": "08/12/1957"}}}, {"id": 1368716, "name": "Willem Steygerwald", "position": "Forward", "dateOfBirth": "", "nationality": ["Netherlands"], "trophies": {"Eredivisie": {"titles": 1, "apps": 2, "seasonsPlayed": 1, "numOfTeamsWithTitles": 1, "TeamsWithTitles": ["AVV DOS Utrecht"], "SeasonsWithTitles": ["57/58"]}}, "leagues": {"Eredivisie": {"debutClub": "AVV DOS Utrecht", "debutAgainst": "Ajax Amsterdam", "debutDate": "01.12.1957", "debutResult": "1:0", "debutOutcome": "loss", "ageAtDebut": "22 years 01 month 06 days", "apps": 2, "debut": "01/12/1957"}}}, {"id": 1368757, "name": "Antonio Marín", "position": "Defender", "dateOfBirth": "", "nationality": ["Spain"], "leagues": {"La Liga": {"apps": 0, "debut": ""}}}, {"id": 1368765, "name": "Roy Carey", "position": "Midfielder", "dateOfBirth": "19.11.1931", "nationality": ["England"], "clubs": {"PSV Eindhoven": {"apps": 1, "goals": 0, "assists": 0, "ownGoals": 0, "yellowCards": 0, "secondYellows": 0, "redCards": 0, "subOn": 0, "subOff": 0, "minutes": 90}}, "leagues": {"Eredivisie": {"debutClub": "PSV Eindhoven", "debutAgainst": "Fortuna '54 (- 1968)", "debutDate": "30.03.1958", "debutResult": "1:0", "debutOutcome": "loss", "ageAtDebut": "26 years 04 months 11 days", "apps": 1, "debut": "30/03/1958"}}}, {"id": 1368785, "name": "Henk van der Velden", "position": "Forward", "dateOfBirth": "", "nationality": ["Netherlands"], "leagues": {"Eredivisie": {"debutClub": "NOAD Tilburg", "debutAgainst": "Ajax Amsterdam", "debutDate": "16.03.1958", "debutResult": "1:0", "debutOutcome": "loss", "ageAtDebut": "19 years 02 months 12 days", "apps": 2, "debut": "16/03/1958"}}}, {"id": 1368790, "name": "Bob Bouber", "position": "Goalkeeper", "dateOfBirth": "", "nationality": ["Netherlands"], "leagues": {"Eredivisie": {"debutClub": "BVC Amsterdam", "debutAgainst": "BVC Amsterdam (- 1958)", "debutDate": "13.04.1958", "debutResult": "2:1", "debutOutcome": "win", "ageAtDebut": "22 years 07 months 07 days", "apps": 7, "debut": "13/04/1958"}}}, {"id": 1368791, "name": "Jan Eype", "position": "Goalkeeper", "dateOfBirth": "", "nationality": ["Netherlands"], "leagues": {"Eredivisie": {"debutClub": "SV Blauw-Wit", "debutAgainst": "ASV Blauw-Wit", "debutDate": "16.03.1958", "debutResult": "1:1", "debutOutcome": "draw", "ageAtDebut": "26 years 06 months 16 days", "apps": 14, "debut": "16/03/1958"}}}, {"id": 1368804, "name": "Kees Smulders", "position": "Forward", "dateOfBirth": "", "nationality": ["Netherlands"], "leagues": {"Eredivisie": {"debutClub": "NOAD Tilburg", "debutAgainst": "MVV Maastricht", "debutDate": "02.02.1958", "debutResult": "2:3", "debutOutcome": "loss", "ageAtDebut": "-", "apps": 1, "debut": "02/02/1958"}}}, {"id": 1368805, "name": "Cor Out", "position": "Midfielder", "dateOfBirth": "", "nationality": ["Netherlands"], "leagues": {"Eredivisie": {"debutClub": "BVC Amsterdam", "debutAgainst": "VV DOS Utrecht", "debutDate": "16.02.1958", "debutResult": "3:1", "debutOutcome": "loss", "ageAtDebut": "21 years 02 months 23 days", "apps": 6, "debut": "16/02/1958"}}}, {"id": 1368806, "name": "Wil Walhout", "position": "Midfielder", "dateOfBirth": "", "nationality": ["Netherlands"], "leagues": {"Eredivisie": {"debutClub": "NOAD Tilburg", "debutAgainst": "ASV Blauw-Wit", "debutDate": "12.01.1958", "debutResult": "1:0", "debutOutcome": "win", "ageAtDebut": "24 years 02 months 23 days", "apps": 18, "debut": "12/01/1958"}}}, {"id": 1368807, "name": "Hans Driesen", "position": "Forward", "dateOfBirth": "", "nationality": ["Netherlands"], "leagues": {"Eredivisie": {"debutClub": "BVC Amsterdam", "debutAgainst": "BVC Amsterdam (- 1958)", "debutDate": "12.01.1958", "debutResult": "0:0", "debutOutcome": "draw", "ageAtDebut": "-", "apps": 1, "debut": "12/01/1958"}}}, {"id": 1368813, "name": "Herbert Kalz", "position": "Forward", "dateOfBirth": "", "nationality": ["Netherlands"], "leagues": {"Eredivisie": {"debutClub": "Rapid JC", "debutAgainst": "Rapid JC (- 1962)", "debutDate": "05.01.1958", "debutResult": "4:1", "debutOutcome": "win", "ageAtDebut": "22 years 10 months 09 days", "apps": 2, "debut": "05/01/1958"}}}, {"id": 1368814, "name": "Joop Koops", "position": "Goalkeeper", "dateOfBirth": "", "nationality": ["Netherlands"], "leagues": {"Eredivisie": {"debutClub": "GVAV Groningen", "debutAgainst": "FC Groningen", "debutDate": "05.01.1958", "debutResult": "1:7", "debutOutcome": "loss", "ageAtDebut": "26 years 00 days", "apps": 2, "debut": "05/01/1958"}}}, {"id": 1368815, "name": "Eddy Bakker", "position": "Goalkeeper", "dateOfBirth": "", "nationality": ["Netherlands"], "leagues": {"Eredivisie": {"debutClub": "GVAV Groningen", "debutAgainst": "FC Groningen", "debutDate": "22.12.1957", "debutResult": "3:3", "debutOutcome": "draw", "ageAtDebut": "26 years 12 days", "apps": 2, "debut": "22/12/1957"}}}, {"id": 1368834, "name": "Piet Wolff", "position": "Forward", "dateOfBirth": "", "nationality": ["Netherlands"], "trophies": {"Eredivisie": {"titles": 1, "apps": 1, "seasonsPlayed": 1, "numOfTeamsWithTitles": 1, "TeamsWithTitles": ["AVV DOS Utrecht"], "SeasonsWithTitles": ["57/58"]}}, "leagues": {"Eredivisie": {"debutClub": "AVV DOS Utrecht", "debutAgainst": "VVV-Venlo", "debutDate": "15.12.1957", "debutResult": "0:0", "debutOutcome": "draw", "ageAtDebut": "21 years 04 months 10 days", "apps": 1, "debut": "15/12/1957"}}}, {"id": 1368889, "name": "Frits Fooy", "position": "Goalkeeper", "dateOfBirth": "", "nationality": ["Netherlands"], "leagues": {"Eredivisie": {"debutClub": "MVV Maastricht", "debutAgainst": "SC Enschede", "debutDate": "01.06.1958", "debutResult": "2:1", "debutOutcome": "win", "ageAtDebut": "19 years 03 months 27 days", "apps": 12, "debut": "01/06/1958"}}}, {"id": 1368892, "name": "Zeki Türkkuşu", "position": "Forward", "dateOfBirth": "", "nationality": ["Türkiye"], "leagues": {"Süper Lig": {"debutClub": "Göztepe", "debutAgainst": "Feriköy", "debutDate": "04.05.1968", "debutResult": "9:1", "debutOutcome": "win", "ageAtDebut": "19 years 04 months 02 days", "apps": 1, "debut": "04/05/1968"}}}, {"id": 1368895, "name": "Matthew Broughton", "position": "", "dateOfBirth": "08.10.1880", "nationality": ["England"], "clubs": {"Nottingham Forest": {"apps": 3, "goals": 1, "assists": 0, "ownGoals": 0, "yellowCards": 0, "secondYellows": 0, "redCards": 0, "subOn": 0, "subOff": 0, "minutes": 270}}}, {"id": 1368900, "name": "Frits de Lange", "position": "Defender", "dateOfBirth": "", "nationality": ["Netherlands"], "leagues": {"Eredivisie": {"debutClub": "SHS Den Haag", "debutAgainst": "ADO Den Haag", "debutDate": "31.08.1958", "debutResult": "3:2", "debutOutcome": "loss", "ageAtDebut": "25 years 11 days", "apps": 19, "debut": "31/08/1958"}}}, {"id": 1368903, "name": "Wim van Elderen", "position": "Defender", "dateOfBirth": "", "nationality": ["Netherlands"], "leagues": {"Eredivisie": {"debutClub": "SHS Den Haag", "debutAgainst": "Holland Sport (- 1971)", "debutDate": "24.08.1958", "debutResult": "2:2", "debutOutcome": "draw", "ageAtDebut": "20 years 05 months 22 days", "apps": 9, "debut": "24/08/1958"}}}, {"id": 1368904, "name": "Frans Kramer", "position": "Goalkeeper", "dateOfBirth": "", "nationality": ["Netherlands"], "leagues": {"Eredivisie": {"debutClub": "DWS/Amsterdam", "debutAgainst": "Ajax Amsterdam", "debutDate": "24.08.1958", "debutResult": "0:1", "debutOutcome": "win", "ageAtDebut": "28 years 04 months 24 days", "apps": 4, "debut": "24/08/1958"}}}, {"id": 1368929, "name": "William Wilson", "position": "", "dateOfBirth": "", "nationality": ["England"], "clubs": {"Newcastle United": {"apps": 4, "goals": 0, "assists": 0, "ownGoals": 0, "yellowCards": 0, "secondYellows": 0, "redCards": 0, "subOn": 0, "subOff": 0, "minutes": 360}}}, {"id": 1368983, "name": "Müjdat Özgür", "position": "Left-Back", "dateOfBirth": "", "nationality": ["Türkiye"], "leagues": {"Süper Lig": {"debutClub": "Feriköy Genclik Kulübü", "debutAgainst": "Fenerbahce", "debutDate": "10.09.1967", "debutResult": "3:0", "debutOutcome": "loss", "ageAtDebut": "22 years 04 months 05 days", "apps": 4, "debut": "10/09/1967"}}}]